i8t/__init__.py
i8t/cli.py
i8t/client.py
i8t/inmemory_storage.py
i8t/relay_consumer.py
i8t/relay_storage.py
i8t/storage.py
i8t/test_client.py
i8t/test_collect.py
i8t/test_inmemory_storage.py
i8t/adapters/__init__.py
i8t/adapters/decorator_adapter/__init__.py
i8t/adapters/decorator_adapter/exporter.py
i8t/adapters/decorator_adapter/loader.py
i8t/adapters/decorator_adapter/serde.py
i8t/adapters/flask_adapter/__init__.py
i8t/adapters/flask_adapter/exporter.py
i8t/adapters/flask_adapter/loader.py
i8t/adapters/requests_adapter/__init__.py
i8t/adapters/requests_adapter/exporter.py
i8t/adapters/requests_adapter/loader.py
i8t/instrument/__init__.py
i8t/instrument/decorator_introspect.py
i8t/instrument/flask_introspect.py
i8t/instrument/requests_introspect.py
i8t/instrument/test_decorator_introspect.py
i8t/instrument/test_flask_introspect.py
i8t/instrument/test_requests_introspect.py
i8t/testing/__init__.py
i8t/testing/session.py
i8t/testing/time_range.py
i8t-0.0.12.dist-info/LICENSE
i8t-0.0.12.dist-info/METADATA
i8t-0.0.12.dist-info/WHEEL
i8t-0.0.12.dist-info/entry_points.txt
i8t-0.0.12.dist-info/top_level.txt
i8t-0.0.12.dist-info/RECORD
