Metadata-Version: 2.1
Name: i8t
Version: 0.0.12
Home-page: https://github.com/peterdemin/i8t
Author: Peter Demin
Author-email: peterdemin@gmail.com
Classifier: Development Status :: 4 - Beta
Classifier: Intended Audience :: Developers
Classifier: License :: OSI Approved :: MIT License
Classifier: Programming Language :: Python :: 3
Classifier: Programming Language :: Python :: 3 :: Only
Requires-Python: >=3.8
License-File: LICENSE
Requires-Dist: requests
Requires-Dist: dill
